README.txt
setup.py
mongonose/__init__.py
mongonose.egg-info/PKG-INFO
mongonose.egg-info/SOURCES.txt
mongonose.egg-info/dependency_links.txt
mongonose.egg-info/entry_points.txt
mongonose.egg-info/requires.txt
mongonose.egg-info/top_level.txt
mongonose.egg-info/zip-safe