Metadata-Version: 1.0
Name: mongonose
Version: 0.5.0
Summary: Nose plugin for automating mongodb for tests runs.
Home-page: http://pypi.python.org/pypi/mongonose
Author: Kapil Thangavelu
Author-email: kapil.foss@gmail.com
License: BSD-derived
Platform: UNKNOWN
Classifier: Environment :: Plugins
Classifier: Intended Audience :: Developers
Classifier: Programming Language :: Python
Classifier: Operating System :: OS Independent
Classifier: Topic :: Internet :: WWW/HTTP
